gembox/__init__.py
gembox/collection_utils/__init__.py
gembox/collection_utils/collection.py
gembox/date_utils/__init__.py
gembox/date_utils/date_utils.py
gembox/debug_utils/__init__.py
gembox/debug_utils/debug_utils.py
gembox/format_utils/__init__.py
gembox/format_utils/format.py
gembox/io/__init__.py
gembox/io/_io.py
gembox/io/pandas_io.py
gembox/io/text_reader.py
gembox/multiprocess/__init__.py
gembox/multiprocess/parallel_executor.py
gembox/multiprocess/task.py
gembox/multiprocess/task_spliter.py
gembox/openai_util/__init__.py
gembox/openai_util/_openai_util.py
gembox/pandas_util/__init__.py
gembox/pandas_util/pd_utils.py
gembox/re_utils/__init__.py
gembox/re_utils/re_utils.py
gembox/scripts/__init__.py
gembox/scripts/ls_py.py
gembox-0.2.0.dist-info/METADATA
gembox-0.2.0.dist-info/WHEEL
gembox-0.2.0.dist-info/entry_points.txt
gembox-0.2.0.dist-info/top_level.txt
gembox-0.2.0.dist-info/RECORD
