Metadata-Version: 2.1
Name: gembox
Version: 0.2.0
Summary: This is the gembox toolbox for steve flyer. You can also find your hammers here.
Home-page: https://github.com/stevieflyer/gembox
Author: Steve Flyer
Author-email: steveflyer7@gmail.com
